cratonapi/__init__.py
cratonapi/dataconnector.py
cratonapi/datacontainers/__init__.py
cratonapi/datacontainers/color.py
cratonapi/datacontainers/cube.py
cratonapi/datacontainers/cubedataslice.py
cratonapi/datacontainers/cubeinfo.py
cratonapi/datacontainers/curve.py
cratonapi/datacontainers/curvedisplayproperties.py
cratonapi/datacontainers/curveinfo.py
cratonapi/datacontainers/grid.py
cratonapi/datacontainers/griddisplayproperties.py
cratonapi/datacontainers/gridinfo.py
cratonapi/datacontainers/outline.py
cratonapi/datacontainers/outlineinfo.py
cratonapi/datacontainers/stratigraphiclevel.py
cratonapi/datacontainers/transformmatrix.py
cratonapi/datacontainers/well.py
cratonapi/datacontainers/wellcurve.py
cratonapi/datacontainers/wellhodograph.py
cratonapi/datacontainers/wellinfo.py
cratonapi/datacontainers/wellstratigraphiclevel.py
cratonapi/datacontainers/welltrajectory.py
cratonapi/exceptions/__init__.py
cratonapi/exceptions/exceptions.py
cratonapi/ioconnections/__init__.py
cratonapi/ioconnections/iobase.py
cratonapi/ioconnections/iofile.py
cratonapi/ioconnections/iopipe.py
cratonapi/ioconnections/ioreader.py
cratonapi/ioconnections/iosocket.py
cratonapi/parsers/__init__.py
cratonapi/parsers/dataparsers/__init__.py
cratonapi/parsers/dataparsers/cubedatarangeparser.py
cratonapi/parsers/dataparsers/cubehorizonsparser.py
cratonapi/parsers/dataparsers/cubepropertiesparser.py
cratonapi/parsers/dataparsers/cubesaroundpointparser.py
cratonapi/parsers/dataparsers/cubesparser.py
cratonapi/parsers/dataparsers/curvedisplaypropertiesparser.py
cratonapi/parsers/dataparsers/curvelistparser.py
cratonapi/parsers/dataparsers/griddisplaypropertiesparser.py
cratonapi/parsers/dataparsers/gridlistparser.py
cratonapi/parsers/dataparsers/gridparser.py
cratonapi/parsers/dataparsers/gridspparser.py
cratonapi/parsers/dataparsers/outlinelistparser.py
cratonapi/parsers/dataparsers/outlineparser.py
cratonapi/parsers/dataparsers/stratigraphiclevelsparser.py
cratonapi-0.1.0.22.dist-info/METADATA
cratonapi-0.1.0.22.dist-info/WHEEL
cratonapi-0.1.0.22.dist-info/RECORD
